exex_cli/__main__.py
exex_cli/application.py
exex_cli/commands.py
exex_cli/convert.py
exex_cli/formats.py
exex_cli/util.py
exex_cli-1.0.3.dist-info/LICENSE
exex_cli-1.0.3.dist-info/WHEEL
exex_cli-1.0.3.dist-info/METADATA
exex_cli-1.0.3.dist-info/RECORD
